torch_sci/__init__.py
torch_sci-1.0.0.dist-info/METADATA
torch_sci-1.0.0.dist-info/WHEEL
torch_sci-1.0.0.dist-info/licenses/LICENSE
torch_sci-1.0.0.dist-info/RECORD
