Metadata-Version: 2.4
Name: torch-sci
Version: 1.0.0
Summary: Differentiable PyTorch functions to calculate scientific notation.
License-File: LICENSE
Requires-Python: >=3.10
Provides-Extra: pytorch
Requires-Dist: torch>=2.5.1; extra == 'pytorch'
